oiko_ai/__init__.py
oiko_ai/agents/__init__.py
oiko_ai/agents/generic_agent_with_tools.py
oiko_ai/memory/__init__.py
oiko_ai/memory/kmessage.py
oiko_ai/prompts/__init__.py
oiko_ai/prompts/basic_prompt.py
oiko_ai/toolkits/__init__.py
oiko_ai/toolkits/database.py
oiko_ai/tools/__init__.py
oiko_ai/tools/consult_database.py
oiko_ai/tools/generic_tool.py
oiko_ai/tools/show_database.py
oiko_ai/tools/write_database.py
oiko_ai/utils/__init__.py
oiko_ai/utils/database_connection.py
oiko_ai/utils/file_extract_toolkit.py
oiko_ai/utils/standard_chatbot_schema.py
oiko_ai/utils/standard_models.py
oiko_ai-0.1.0.dist-info/METADATA
oiko_ai-0.1.0.dist-info/WHEEL
oiko_ai-0.1.0.dist-info/RECORD
